cwl_tes/__init__.py
cwl_tes/ftp.py
cwl_tes/main.py
cwl_tes/tes.py
tests/__init__.py
tests/funnel_test_util.py
tests/test_conformance.py
cwl_tes-0.3.0.dist-info/LICENSE
cwl_tes-0.3.0.dist-info/METADATA
cwl_tes-0.3.0.dist-info/WHEEL
cwl_tes-0.3.0.dist-info/entry_points.txt
cwl_tes-0.3.0.dist-info/top_level.txt
cwl_tes-0.3.0.dist-info/zip-safe
cwl_tes-0.3.0.dist-info/RECORD
