Metadata-Version: 2.1
Name: cwl-tes
Version: 0.3.0
Summary: Common workflow language reference implementation backended     by a GA4GH Task Execution Service
Home-page: https://github.com/common-workflow-language/cwl-tes
Author: Adam Struck
Author-email: strucka@ohsu.edu
License: Apache 2.0
Platform: UNKNOWN
Classifier: Development Status :: 3 - Alpha
Classifier: Natural Language :: English
Classifier: License :: OSI Approved :: Apache Software License
Classifier: Programming Language :: Python :: 2.7
Classifier: Programming Language :: Python :: 3.5
Classifier: Programming Language :: Python :: 3.6
Classifier: Programming Language :: Python :: 3.7
Requires-Python: >=2.7, !=3.0.*, !=3.1.*, !=3.2.*, !=3.3.*, !=3.4.*, <4
Requires-Dist: cwltool (==1.0.20191022103248)
Requires-Dist: future (>=0.16.0)
Requires-Dist: py-tes (>=0.4.0)
Requires-Dist: PyJWT (>=1.6.4)
Requires-Dist: requests (>=2.14.2)
Requires-Dist: typing-extensions (>=3.7.4)
Provides-Extra: test
Requires-Dist: cwltest (>=1.0.20190228134645) ; extra == 'test'
Requires-Dist: nose (>=1.3.7) ; extra == 'test'
Requires-Dist: flake8 (>=3.7.0) ; extra == 'test'
Requires-Dist: PyYAML (>=3.12) ; extra == 'test'
